fractal_specifications/__init__.py
fractal_specifications/py.typed
fractal_specifications/contrib/__init__.py
fractal_specifications/contrib/django/__init__.py
fractal_specifications/contrib/django/specifications.py
fractal_specifications/contrib/duckdb/__init__.py
fractal_specifications/contrib/duckdb/specifications.py
fractal_specifications/contrib/elasticsearch/__init__.py
fractal_specifications/contrib/elasticsearch/specifications.py
fractal_specifications/contrib/google_firestore/__init__.py
fractal_specifications/contrib/google_firestore/specifications.py
fractal_specifications/contrib/mongo/__init__.py
fractal_specifications/contrib/mongo/specifications.py
fractal_specifications/contrib/pandas/__init__.py
fractal_specifications/contrib/pandas/specifications.py
fractal_specifications/contrib/postgresql/__init__.py
fractal_specifications/contrib/postgresql/specifications.py
fractal_specifications/contrib/sqlalchemy/__init__.py
fractal_specifications/contrib/sqlalchemy/specifications.py
fractal_specifications/generic/__init__.py
fractal_specifications/generic/collections.py
fractal_specifications/generic/dsl_parser.py
fractal_specifications/generic/operators.py
fractal_specifications/generic/specification.py
fractal_specifications-3.4.2.dist-info/licenses/LICENSE
fractal_specifications-3.4.2.dist-info/WHEEL
fractal_specifications-3.4.2.dist-info/METADATA
fractal_specifications-3.4.2.dist-info/RECORD
