Metadata-Version: 2.4
Name: fractal-specifications
Version: 3.4.2
Summary: Fractal Specifications is an implementation of the specification pattern for building SOLID logic for your Python applications.
Keywords: specification,pattern,solid,database,query,sql,mongodb
Author-email: Douwe van der Meij <douwe@karibu-online.nl>
Requires-Python: >=3.10
Classifier: Development Status :: 5 - Production/Stable
Classifier: Environment :: Web Environment
Classifier: Intended Audience :: Developers
Classifier: License :: OSI Approved :: MIT License
Classifier: Operating System :: OS Independent
Classifier: Programming Language :: Python :: 3
Classifier: Programming Language :: Python :: 3.10
Classifier: Programming Language :: Python :: 3.11
Classifier: Programming Language :: Python :: 3.12
Classifier: Programming Language :: Python :: 3.13
Classifier: Topic :: Software Development :: Libraries :: Python Modules
Classifier: Topic :: Database
License-File: LICENSE
Requires-Dist: lark
Requires-Dist: django>=4.2.25 ; extra == "dev"
Requires-Dist: pandas>=2.0.3 ; extra == "dev"
Requires-Dist: duckdb>=0.9.0 ; extra == "dev"
Requires-Dist: pytest>=7.0.0 ; extra == "dev"
Requires-Dist: pytest-cov>=4.0.0 ; extra == "dev"
Requires-Dist: pytest-asyncio>=0.21.0 ; extra == "dev"
Requires-Dist: black>=23.0.0 ; extra == "dev"
Requires-Dist: ruff>=0.1.0 ; extra == "dev"
Requires-Dist: mypy>=1.0.0 ; extra == "dev"
Requires-Dist: isort>=5.13.2 ; extra == "dev"
Requires-Dist: django>=4.2.25 ; extra == "django"
Requires-Dist: duckdb>=0.9.0 ; extra == "duckdb"
Requires-Dist: pandas>=2.0.3 ; extra == "pandas"
Project-URL: Documentation, https://github.com/douwevandermeij/fractal-specifications#readme
Project-URL: Homepage, https://github.com/douwevandermeij/fractal-specifications
Project-URL: Issues, https://github.com/douwevandermeij/fractal-specifications/issues
Project-URL: Repository, https://github.com/douwevandermeij/fractal-specifications
Provides-Extra: dev
Provides-Extra: django
Provides-Extra: duckdb
Provides-Extra: pandas
